ms_image_tool/__init__.py
ms_image_tool/image.py
ms_image_tool-1.0.1.dist-info/LICENSE
ms_image_tool-1.0.1.dist-info/METADATA
ms_image_tool-1.0.1.dist-info/WHEEL
ms_image_tool-1.0.1.dist-info/RECORD
